Regexes/__init__.py
Regexes/regexes.py
Regexes/utils/__init__.py
Regexes/utils/strings.py
Regexes-0.0.3.dist-info/LICENSE
Regexes-0.0.3.dist-info/METADATA
Regexes-0.0.3.dist-info/WHEEL
Regexes-0.0.3.dist-info/top_level.txt
Regexes-0.0.3.dist-info/RECORD
