Metadata-Version: 2.1
Name: Regexes
Version: 0.0.3
Summary: Common Regexes via Python
Author: Yusuf Berkay Girgin
Project-URL: Homepage, https://github.com/ybgirgin3/Regexes
Classifier: Programming Language :: Python :: 3
Classifier: License :: OSI Approved :: GNU General Public License v3 or later (GPLv3+)
Classifier: Operating System :: OS Independent
Requires-Python: >=3.9
License-File: LICENSE
